gadgethiServerUtils/GadgethiAWSHandler.py
gadgethiServerUtils/GadgethiClient.py
gadgethiServerUtils/GadgethiServer.py
gadgethiServerUtils/GadgethiZMQ.py
gadgethiServerUtils/__init__.py
gadgethiServerUtils/_configs.py
gadgethiServerUtils/_exceptions.py
gadgethiServerUtils/authentication.py
gadgethiServerUtils/db_basics.py
gadgethiServerUtils/db_operations.py
gadgethiServerUtils/encryption.py
gadgethiServerUtils/file_basics.py
gadgethiServerUtils/main.py
gadgethiServerUtils/pay_integration.py
gadgethiServerUtils/time_basics.py
gadgethiServerUtils/scripts/__init__.py
gadgethiServerUtils/scripts/generate_configs.py
gadgethiServerUtils/tests/__init__.py
gadgethiServerUtils/tests/testAWSHandler.py
gadgethiServerUtils/tests/testAuth.py
gadgethiServerUtils/tests/testGserver.py
gadgethiServerUtils/tests/testPrimitives.py
gadgethiServerUtils/tests/testScripts.py
gadgethiServerUtils/tests/testTime.py
gadgethiServerUtils-999.999.dist-info/METADATA
gadgethiServerUtils-999.999.dist-info/WHEEL
gadgethiServerUtils-999.999.dist-info/entry_points.txt
gadgethiServerUtils-999.999.dist-info/top_level.txt
gadgethiServerUtils-999.999.dist-info/RECORD
