Metadata-Version: 2.1
Name: gadgethiServerUtils
Version: 999.999
Summary: Gadgethi server maintenance package
Home-page: https://github.com/weitung/gadgethiServerUtils.git
Author: Gadgethi Develop Team
Author-email: developers@gadget-hitech.com
License: AGPLv3+
Platform: UNKNOWN
Classifier: Intended Audience :: Developers
Classifier: License :: OSI Approved :: GNU Affero General Public License v3 or later (AGPLv3+)
Classifier: Programming Language :: Python :: 3.5
Classifier: Programming Language :: Python :: 3.6
Classifier: Programming Language :: Python :: 3.7
Classifier: Operating System :: OS Independent
Classifier: Topic :: Software Development :: Libraries 
Requires-Python: >=3.5
Requires-Dist: pycryptodomex
Requires-Dist: pyyaml (==5.1)
Requires-Dist: boto3
Requires-Dist: discover
Requires-Dist: requests
